pttoolbox/__init__.py
pttoolbox/version.py
pttoolbox-0.0.1.dist-info/LICENSE
pttoolbox-0.0.1.dist-info/METADATA
pttoolbox-0.0.1.dist-info/WHEEL
pttoolbox-0.0.1.dist-info/top_level.txt
pttoolbox-0.0.1.dist-info/RECORD
